galaxy/__init__.py
galaxy/containers/__init__.py
galaxy/containers/docker.py
galaxy/containers/docker_decorators.py
galaxy/containers/docker_model.py
galaxy/containers/docker_swarm.py
galaxy/exceptions/__init__.py
galaxy/exceptions/error_codes.json
galaxy/exceptions/error_codes.py
galaxy/jobs/__init__.py
galaxy/jobs/metrics/__init__.py
galaxy/jobs/metrics/formatting.py
galaxy/jobs/metrics/collectl/__init__.py
galaxy/jobs/metrics/collectl/cli.py
galaxy/jobs/metrics/collectl/processes.py
galaxy/jobs/metrics/collectl/stats.py
galaxy/jobs/metrics/collectl/subsystems.py
galaxy/jobs/metrics/instrumenters/__init__.py
galaxy/jobs/metrics/instrumenters/cgroup.py
galaxy/jobs/metrics/instrumenters/collectl.py
galaxy/jobs/metrics/instrumenters/core.py
galaxy/jobs/metrics/instrumenters/cpuinfo.py
galaxy/jobs/metrics/instrumenters/env.py
galaxy/jobs/metrics/instrumenters/hostname.py
galaxy/jobs/metrics/instrumenters/meminfo.py
galaxy/jobs/metrics/instrumenters/uname.py
galaxy/objectstore/__init__.py
galaxy/objectstore/azure_blob.py
galaxy/objectstore/cloud.py
galaxy/objectstore/pithos.py
galaxy/objectstore/pulsar.py
galaxy/objectstore/rods.py
galaxy/objectstore/s3.py
galaxy/objectstore/s3_multipart_upload.py
galaxy/tools/__init__.py
galaxy/tools/fetcher.py
galaxy/tools/hash.py
galaxy/tools/lint.py
galaxy/tools/lint_util.py
galaxy/tools/loader.py
galaxy/tools/loader_directory.py
galaxy/tools/cwl/__init__.py
galaxy/tools/cwl/cwltool_deps.py
galaxy/tools/cwl/parser.py
galaxy/tools/cwl/representation.py
galaxy/tools/cwl/runtime_actions.py
galaxy/tools/cwl/schema.py
galaxy/tools/cwl/util.py
galaxy/tools/deps/__init__.py
galaxy/tools/deps/brew_exts.py
galaxy/tools/deps/brew_util.py
galaxy/tools/deps/commands.py
galaxy/tools/deps/conda_compat.py
galaxy/tools/deps/conda_util.py
galaxy/tools/deps/container_classes.py
galaxy/tools/deps/containers.py
galaxy/tools/deps/dependencies.py
galaxy/tools/deps/docker_util.py
galaxy/tools/deps/dockerfiles.py
galaxy/tools/deps/installable.py
galaxy_lib-19.5.2.dist-info/LICENSE
galaxy_lib-19.5.2.dist-info/METADATA
galaxy_lib-19.5.2.dist-info/WHEEL
galaxy_lib-19.5.2.dist-info/entry_points.txt
galaxy_lib-19.5.2.dist-info/top_level.txt
galaxy_lib-19.5.2.dist-info/RECORD
