Metadata-Version: 1.1
Name: galaxy-lib
Version: 19.5.2
Summary: Subset of Galaxy (http://galaxyproject.org/) core code base designed to be used a library.
Home-page: https://github.com/galaxyproject/galaxy-lib
Author: Galaxy Project and Community
Author-email: jmchilton@gmail.com
License: AFL
Keywords: galaxy
Platform: UNKNOWN
Classifier: Development Status :: 5 - Production/Stable
Classifier: Intended Audience :: Developers
Classifier: Environment :: Console
Classifier: License :: OSI Approved :: Academic Free License (AFL)
Classifier: Operating System :: POSIX
Classifier: Topic :: Software Development
Classifier: Topic :: Software Development :: Code Generators
Classifier: Topic :: Software Development :: Testing
Classifier: Natural Language :: English
Classifier: Programming Language :: Python :: 2
Classifier: Programming Language :: Python :: 2.7
Classifier: Programming Language :: Python :: 3.4
Classifier: Programming Language :: Python :: 3.5
Classifier: Programming Language :: Python :: 3.6
Classifier: Programming Language :: Python :: 3.7
